aigremlins.py
aigremlins-1.3.dist-info/WHEEL
aigremlins-1.3.dist-info/METADATA
aigremlins-1.3.dist-info/RECORD
