Metadata-Version: 2.1
Name: aigremlins
Version: 1.3
Summary: Using GPT 3 to backstop buggy code
License: MIT
Author: Ivan Thung
Author-email: ivanthung@gmail.com
Requires-Python: >=3.9.10,<4.0.0
Classifier: License :: OSI Approved :: MIT License
Classifier: Programming Language :: Python :: 3
Classifier: Programming Language :: Python :: 3.10
Classifier: Programming Language :: Python :: 3.11
Requires-Dist: openai (>=0.27.2,<0.28.0)
